README.md
setup.py
ssh_scanner/__init__.py
ssh_scanner/app.py
ssh_scanner/bin.py
ssh_scanner/db.py
ssh_scanner.egg-info/PKG-INFO
ssh_scanner.egg-info/SOURCES.txt
ssh_scanner.egg-info/dependency_links.txt
ssh_scanner.egg-info/entry_points.txt
ssh_scanner.egg-info/requires.txt
ssh_scanner.egg-info/top_level.txt